grata/__init__.py
grata/_base_client.py
grata/_client.py
grata/_compat.py
grata/_constants.py
grata/_exceptions.py
grata/_files.py
grata/_models.py
grata/_qs.py
grata/_resource.py
grata/_response.py
grata/_streaming.py
grata/_types.py
grata/_version.py
grata/py.typed
grata/_utils/__init__.py
grata/_utils/_logs.py
grata/_utils/_proxy.py
grata/_utils/_reflection.py
grata/_utils/_streams.py
grata/_utils/_sync.py
grata/_utils/_transform.py
grata/_utils/_typing.py
grata/_utils/_utils.py
grata/lib/.keep
grata/resources/__init__.py
grata/resources/enrichments.py
grata/resources/lists.py
grata/resources/searches.py
grata/types/__init__.py
grata/types/bulk_enrich_response.py
grata/types/company.py
grata/types/conference.py
grata/types/contact.py
grata/types/enrichment_bulk_enrich_params.py
grata/types/enrichment_enrich_params.py
grata/types/industry_classification.py
grata/types/investors.py
grata/types/list.py
grata/types/list_companies_params.py
grata/types/list_create_params.py
grata/types/list_list_params.py
grata/types/list_response.py
grata/types/list_update_params.py
grata/types/location.py
grata/types/owner.py
grata/types/search_list_response.py
grata/types/search_response.py
grata/types/search_search_params.py
grata/types/search_search_similar_params.py
grata/types/similar_search_response.py
grata/types/software_industry_classification.py
grata-1.1.2.dist-info/METADATA
grata-1.1.2.dist-info/WHEEL
grata-1.1.2.dist-info/licenses/LICENSE
grata-1.1.2.dist-info/RECORD
